[
  {
    "count": 1,
    "zekr": "قال الله تعالى: ” الَّذِينَ آمَنُواْ وَتَطْمَئِنُّ قُلُوبُهُم بِذِكْرِ اللّهِ أَلاَ بِذِكْرِ اللّهِ تَطْمَئِنُّ الْقُلُوبُ “\n\nهيا فلنبدأ معا بقراءة أذكار الصباح 😊\n\n(يمكنك تشغيل الصوت هنا لسماع الأذكار كاملة، أو التمرير لسماع كل ذكر على حدة)",
    "source": "",
    "sound": "all_morning.mp3"
  },
  {
    "count": 1,
    "zekr": "بِسْمِ اللهِ الرَّحْمنِ الرَّحِيم ِ\nاللّهُ لاَ إِلَـهَ إِلاَّ هُوَ الْحَيُّ الْقَيُّومُ لاَ تَأْخُذُهُ سِنَةٌ وَلاَ نَوْمٌ لَّهُ مَا فِي السَّمَاوَاتِ وَمَا فِي الأَرْضِ مَن ذَا الَّذِي يَشْفَعُ عِنْدَهُ إِلاَّ بِإِذْنِهِ يَعْلَمُ مَا بَيْنَ أَيْدِيهِمْ وَمَا خَلْفَهُمْ وَلاَ يُحِيطُونَ بِشَيْءٍ مِّنْ عِلْمِهِ إِلاَّ بِمَا شَاء وَسِعَ كُرْسِيُّهُ السَّمَاوَاتِ وَالأَرْضَ وَلاَ يَؤُودُهُ حِفْظُهُمَا وَهُوَ الْعَلِيُّ الْعَظِيمُ\n [آية الكرسي – البقرة 255].",
    "source": "الحَدِيث أخرجه الطَّبَرَانِيّ فِي الْكَبِير كَمَا قَالَ المُصَنّف رَحمَه الله وَهُوَ من حَدِيث ابْن مَسْعُود رَضِي الله عَنهُ بِلَفْظ من قَرَأَ عشر آيَات من أول الْبَقَرَة وَآيَة الْكُرْسِيّ وآيتين بعْدهَا وخواتيمها لم يدْخل ذَلِك الْبَيْت شَيْطَان حَتَّى يصبح وَأخرجه الْحَاكِم وَصَححهُ من حَدِيثه وَأخرج الديلمي فِي مُسْند الفردوس عَن عمرَان بن حُصَيْن رَضِي الله عَنهُ مَرْفُوعا من قَرَأَ فَاتِحَة الْكتاب وَآيَة الْكُرْسِيّ وَلَا يقرؤهما عبد فِي دَار فَيُصِيبهُ ذَلِك الْيَوْم عين أنس أَو جن ويغني عَن هَذَا مَا ثَبت فِي صَحِيح البُخَارِيّ من حَدِيث أبي هُرَيْرَة رَضِي الله عَنهُ",
    "sound": "1.mp3"
  },
  {
    "count": 3,
    "zekr": "بِسْمِ اللهِ الرَّحْمنِ الرَّحِيم ِ\nقُلْ هُوَ ٱللَّهُ أَحَدٌ، ٱللَّهُ ٱلصَّمَدُ، لَمْ يَلِدْ وَلَمْ يُولَدْ، وَلَمْ يَكُن لَّهُۥ كُفُوًا أَحَدٌۢ.",
    "source": " الحَدِيث أخرجه أَبُو دَاوُد وَالتِّرْمِذِيّ كَمَا قَالَ المُصَنّف رَحمَه الله وَهُوَ من حَدِيث معَاذ بن عبد الله ابْن خبيب عَن أَبِيه وَأخرجه أَيْضا النَّسَائِيّ وَقَالَ التِّرْمِذِيّ حسن صَحِيح غَرِيب من هَذَا الْوَجْه وَلَفظ أبي دَاوُد قَالَ خرجنَا فِي لَيْلَة مطر وظلمة شَدِيدَة نطلب رَسُول الله صلى الله عَلَيْهِ وَسلم ليُصَلِّي بِنَا فأدركناه فَقَالَ",
    "sound": "2.mp3"
  },
  {
    "count": 3,
    "zekr": "بِسْمِ اللهِ الرَّحْمنِ الرَّحِيم\nقُلْ أَعُوذُ بِرَبِّ ٱلْفَلَقِ، مِن شَرِّ مَا خَلَقَ، وَمِن شَرِّ غَاسِقٍ إِذَا وَقَبَ، وَمِن شَرِّ ٱلنَّفَّٰثَٰتِ فِى ٱلْعُقَدِ، وَمِن شَرِّ حَاسِدٍ إِذَا حَسَدَ.",
    "source": " الحَدِيث أخرجه أَبُو دَاوُد وَالتِّرْمِذِيّ كَمَا قَالَ المُصَنّف رَحمَه الله وَهُوَ من حَدِيث معَاذ بن عبد الله ابْن خبيب عَن أَبِيه وَأخرجه أَيْضا النَّسَائِيّ وَقَالَ التِّرْمِذِيّ حسن صَحِيح غَرِيب من هَذَا الْوَجْه وَلَفظ أبي دَاوُد قَالَ خرجنَا فِي لَيْلَة مطر وظلمة شَدِيدَة نطلب رَسُول الله صلى الله عَلَيْهِ وَسلم ليُصَلِّي بِنَا فأدركناه فَقَالَ",
    "sound": "3.mp3"
  },
  {
    "count": 3,
    "zekr": "بِسْمِ اللهِ الرَّحْمنِ الرَّحِيم\nقُلْ أَعُوذُ بِرَبِّ ٱلنَّاسِ، مَلِكِ ٱلنَّاسِ، إِلَٰهِ ٱلنَّاسِ، مِن شَرِّ ٱلْوَسْوَاسِ ٱلْخَنَّاسِ، ٱلَّذِى يُوَسْوِسُ فِى صُدُورِ ٱلنَّاسِ، مِنَ ٱلْجِنَّةِ وَٱلنَّاسِ.",
    "source": " الحَدِيث أخرجه أَبُو دَاوُد وَالتِّرْمِذِيّ كَمَا قَالَ المُصَنّف رَحمَه الله وَهُوَ من حَدِيث معَاذ بن عبد الله ابْن خبيب عَن أَبِيه وَأخرجه أَيْضا النَّسَائِيّ وَقَالَ التِّرْمِذِيّ حسن صَحِيح غَرِيب من هَذَا الْوَجْه وَلَفظ أبي دَاوُد قَالَ خرجنَا فِي لَيْلَة مطر وظلمة شَدِيدَة نطلب رَسُول الله صلى الله عَلَيْهِ وَسلم ليُصَلِّي بِنَا فأدركناه فَقَالَ",
    "sound": "4.mp3"
  },
  {
    "count": 1,
    "zekr": "أَصْـبَحْنا وَأَصْـبَحَ المُـلْكُ لله وَالحَمدُ لله، لا إلهَ إلاّ اللّهُ وَحدَهُ لا شَريكَ لهُ، لهُ المُـلكُ ولهُ الحَمْـد، وهُوَ على كلّ شَيءٍ قدير، رَبِّ أسْـأَلُـكَ خَـيرَ ما في هـذا اليوم وَخَـيرَ ما بَعْـدَه، وَأَعـوذُ بِكَ مِنْ شَـرِّ ما في هـذا اليوم وَشَرِّ ما بَعْـدَه، رَبِّ أَعـوذُ بِكَ مِنَ الْكَسَـلِ وَسـوءِ الْكِـبَر، رَبِّ أَعـوذُ بِكَ مِنْ عَـذابٍ في النّـارِ وَعَـذابٍ في القَـبْر. َ",
    "source": "من قالها موقنا بها حين يمسى ومات من ليلته دخل الجنة وكذلك حين يصبح.\nرواه مسلم",
    "sound": "5.mp3"
  },
  {
    "count": 1,
    "zekr": "أَصْبَـحْـنا عَلَى فِطْرَةِ الإسْلاَمِ، وَعَلَى كَلِمَةِ الإِخْلاَصِ، وَعَلَى دِينِ نَبِيِّنَا مُحَمَّدٍ صَلَّى اللهُ عَلَيْهِ وَسَلَّمَ، وَعَلَى مِلَّةِ أَبِينَا إبْرَاهِيمَ حَنِيفاً مُسْلِماً وَمَا كَانَ مِنَ المُشْرِكِينَ.",
    "source": "الحَدِيث أخرجه أَحْمد وَالطَّبَرَانِيّ فِي الْكَبِير كَمَا قَالَ المُصَنّف رَحمَه الله وَهُوَ من حَدِيث عبد الرَّحْمَن بن أَبْزي رَضِي الله عَنهُ وَأخرجه النَّسَائِيّ من حَدِيثه من طَرِيق أُخْرَى رجال إِسْنَاده رجال الصَّحِيح وَلَفظ الحَدِيث قَالَ كَانَ النَّبِي صلى الله عَلَيْهِ وَسلم إِذا أصبح قَالَ أَصْبَحْنَا على فطْرَة الْإِسْلَام وَكلمَة الْإِخْلَاص وعَلى دين نَبينَا مُحَمَّد صلى الله عَلَيْهِ وَسلم وعَلى مِلَّة أَبينَا إِبْرَاهِيم حَنِيفا مُسلما وَمَا كَانَ من الْمُشْركين وَلَفظ أَحْمد وَالطَّبَرَانِيّ كَانَ إِذا أصبح وَإِذا أَمْسَى وَلِهَذَا جعله المُصَنّف من أدعية الصَّباح والمساء وَأخرجه أَيْضا ابْن السّني بِإِسْنَاد صَححهُ النَّوَوِيّ وَقَالَ الهيثمي رجالهما يَعْنِي أَحْمد وَالطَّبَرَانِيّ رجال الصَّحِيح (قَوْله حَنِيفا) قَالَ الْأَزْهَرِي معنى الحنيفية فِي الْإِسْلَام الْميل إِلَيْهِ وَالْإِقَامَة على عقده والحنف إقبال إِحْدَى الْقَدَمَيْنِ على الْأُخْرَى والحنيف الصَّحِيح الْميل إِلَى الْإِسْلَام وَالثَّابِت عَلَيْهِ وَقَالَ ابْن سَيّده فِي محكمه الحنيف الْمُسلم الَّذِي يتحنف عَن الْأَدْيَان أَي يمِيل إِلَى الْحق قَالَ وَقيل هُوَ المخلص والفطرة ابْتِدَاء الْخلقَة وفطرة الْإِسْلَام دين الْإِسْلَام وَمن ذَلِك قَوْله صلى الله عَلَيْهِ وَسلم كل مَوْلُود يُولد على الْفطْرَة وَمِنْه قَوْله سُبْحَانَهُ {فطْرَة الله الَّتِي فطر النَّاس عَلَيْهَا}",
    "sound": "6.mp3"
  },
  {
    "count": 1,
    "zekr": "اللَّهُمَّ بك أَصْبَحْنَا وَبِك أمسينا وَبِك نحيا وَبِك نموت وَإِلَيْك النشور",
    "source": "الحَدِيث أخرجه أهل السّنَن الْأَرْبَع وَابْن حبَان كَمَا قَالَ المُصَنّف  وَهُوَ من حَدِيث أبي هُرَيْرَة  وَقَالَ التِّرْمِذِيّ بعد إِخْرَاجه هَذَا حَدِيث حسن صَحِيح وَصَححهُ ابْن حبَان وَالنَّوَوِيّ وَأخرجه أَحْمد بِإِسْنَاد رِجَاله رجال الصَّحِيح وَرَوَاهُ أَبُو عوَانَة فِي صَحِيحه وَابْن السّني فِي عمل الْيَوْم وَاللَّيْلَة وَأول الحَدِيث بِلَفْظ كَانَ إِذا أصبح يَقُول اللَّهُمَّ بك أَصْبَحْنَا وَعند بعض هَؤُلَاءِ المخرجين لَهُ بِلَفْظ إِذا أَصْبَحْتُم فقد اجْتمع فِي الحَدِيث القَوْل وَالْفِعْل (قَوْله وَإِلَيْك النشور) هَكَذَا فِي بعض نسخ هَذَا الْكتاب وَفِي بَعْضهَا وَإِلَيْك الْمصير وَعَلِيهِ أَكثر أَلْفَاظ المخرجين لهَذَا الحَدِيث وَلكنه خرج هَذَا الحَدِيث وَمَا بعده أَبُو دَاوُد وَالتِّرْمِذِيّ بِلَفْظ كَانَ رَسُول الله ﷺ إِذا أصبح قَالَ اللَّهُمَّ بك أَصْبَحْنَا وَبِك أمسينا وَبِك نحيا وَبِك نموت وَإِلَيْك الْمصير وَإِذا أَمْسَى قَالَ اللَّهُمَّ بك أمسينا وَبِك أَصْبَحْنَا وَبِك نحيا وَبِك نموت وَإِلَيْك النشور فَأفَاد هَذَا أَن لفظ الْمصير فِي الصَّباح وَلَفظ النشور فِي الْمسَاء وَتَقْدِيم بك على أَصْبَحْنَا وَمَا بعده يُفِيد الِاخْتِصَاص وَالْبَاء للاستعانة",
    "sound": "7.mp3"
  },
  {
    "count": 1,
    "zekr": "اللَّهُمَّ مَا أصبح بِي من نعْمَة أَو بِأحد من خلقك فمنك وَحدك لَا شريك لَك فلك الْحَمد وَلَك الشُّكْر",
    "source": "الحَدِيث أخرجه أَبُو دَاوُد وأبن حبَان كَمَا قَالَ المُصَنّف  وَهُوَ من حَدِيث عبد الله بن غَنَّام البياضي وَأخرجه أَيْضا من حَدِيثه النَّسَائِيّ وَصَححهُ ابْن حبَان وجود النَّسَائِيّ إِسْنَاده وَلَفظه أَن رَسُول الله ﷺ قَالَ من قَالَ حِين يصبح اللَّهُمَّ مَا أصبح بِي من نعْمَة أَو بِأحد من خلقك فمنك وَحدك لَا شريك لَك فلك الْحَمد وَلَك الشُّكْر فقد أدّى شكر يَوْمه وَمن قَالَهَا مثل ذَلِك حِين يُمْسِي فقد أدّى شكر ليلته وَأخرجه أَيْضا ابْن حبَان فِي صَحِيحه وَفِيه اللَّهُمَّ مَا أصبح بِي من نعْمَة أَو بِأحد من خلقك وَرَوَاهُ من حَدِيث ابْن عَبَّاس وَفِي الحَدِيث فَضِيلَة عَظِيمَة ومنقبة كَرِيمَة حَيْثُ تكون تأدية وَاجِب الشُّكْر بِهَذِهِ الْأَلْفَاظ الْيَسِيرَة القليلة وَأَن قَائِلهَا صباحا قد أدّى شكر يَوْمه وقائلها مسَاء قد أدّى شكر ليلته مَعَ أَن الله تعالي يَقُول ﴿وَإِن تعدوا نعْمَة الله لَا تحصوها﴾ وَإِذا كَانَت النعم لَا يُمكن إحصاؤها فَكيف يقدر العَبْد على شكرها فَللَّه الْحَمد وَللَّه الشُّكْر على هَذِه الْفَائِدَة الجليلة الْمَأْخُوذَة من مَعْدن الْعلم ومنبعه",
    "sound": "8.mp3"
  },
  {
    "count": 3,
    "zekr": "رَضيـتُ بِاللهِ رَبَّـاً وَبِالإسْلامِ ديـناً وَبِمُحَـمَّدٍ صلى الله عليه وسلم نَبِيّـاً.",
    "source": "الحَدِيث أخرجه باللفظين الْمَذْكُورين من ذكره المُصَنّف  فَالْأول عزاهُ إِلَى أهل السّنَن الْأَرْبَع وَالطَّبَرَانِيّ فِي الْكَبِير وَالثَّانِي عزاهُ إِلَى مُصَنف ابْن أبي شيبَة وَهُوَ من حَدِيث سَلام  خَادِم رَسُول الله ﷺ قَالَ سَمِعت رَسُول الله ﷺ يَقُول من قَالَ إِذا أصبح وَإِذا أَمْسَى رضيت بِاللَّه رَبًّا وَبِالْإِسْلَامِ دينا وَبِمُحَمَّدٍ رَسُولا كَانَ حَقًا على الله أَن يرضيه وَأخرجه أَيْضا من حَدِيثه أَحْمد قَالَ الهيثمي وَرِجَال أَحْمد وَالطَّبَرَانِيّ ثِقَات وَزَاد ثَلَاث مَرَّات وَمن حَدِيثه أخرجه أَيْضا الْحَاكِم فِي الْمُسْتَدْرك وَقَالَ صَحِيح الْإِسْنَاد وَأخرجه أَيْضا التِّرْمِذِيّ من حَدِيث ثَوْبَان بِلَفْظ رضيت بِاللَّه رَبًّا وَبِالْإِسْلَامِ دينا وَبِمُحَمَّدٍ نَبيا وَقَالَ حسن غَرِيب وَأخرجه ابْن أبي شيبَة وَابْن السّني من حَدِيث أبي سعيد  بِلَفْظ رضيت بِاللَّه رَبًّا وَبِالْإِسْلَامِ دينا وَبِمُحَمَّدٍ نَبيا وَزَاد ثَلَاث مَرَّات وَسَلام هَذَا قد ذكره ابْن عبد الْبر فِي الِاسْتِيعَاب وَذكر هَذَا الحَدِيث من حَدِيثه وَقَالَ هَذَا هُوَ الصَّحِيح فِي إِسْنَاد هَذَا الحَدِيث (قَوْله فِي الرِّوَايَة الأولى رَسُولا وَفِي الثَّانِيَة نَبيا) قَالَ النَّوَوِيّ فَيُسْتَحَب أَن يجمع بَينهمَا فَيُقَال نَبيا ورسولا وَلَو اقْتصر على أَحدهمَا لَكَانَ عَاملا بِالْحَدِيثِ",
    "sound": "10.mp3"
  },
  {
    "count": 1,
    "zekr": "اللَّهُمَّ إِنِّي أَسأَلك الْعَافِيَة فِي الدُّنْيَا وَالْآخِرَة اللَّهُمَّ إِنِّي أَسَالَك الْعَفو والعافية فِي ديني ودنياي وَأَهلي وَمَالِي اللَّهُمَّ اسْتُرْ عورتي وَأمن روعتي اللَّهُمَّ احفظني من بَين يَدي وَمن خَلْفي وَعَن يَمِيني وَعَن شمَالي وَمن فَوقِي وَأَعُوذ بعظمتك أَن أغتال من تحتي",
    "source": "الحَدِيث أخرجه أَبُو دَاوُد وَابْن حبَان كَمَا قَالَ المُصَنّف  وَهُوَ من حَدِيث ابْن عمر  مَا وَأخرجه أَيْضا من حَدِيثه النَّسَائِيّ وَابْن ماجة وَالْحَاكِم وَقَالَ صَحِيح الْإِسْنَاد وَصَححهُ أَيْضا ابْن حبَان وَقَالَ النَّوَوِيّ روينَاهُ بِالْأَسَانِيدِ الصَّحِيحَة وَأول الحَدِيث عِنْد أبي دَاوُد وَغَيره بِلَفْظ عَن ابْن عمر  قَالَ لم يكن رَسُول الله ﷺ يدع هَؤُلَاءِ الدَّعْوَات حِين يُمْسِي وَحين يصبح اللَّهُمَّ إِنِّي أَسأَلك الخ (قَوْله اسْتُرْ عورتي وَأمن روعتي) هَكَذَا بِالْإِفْرَادِ عِنْد الْجَمِيع وَعند ابْن أبي شيبَة اللَّهُمَّ اسْتُرْ عوراتي وَأمن روعاتي بِالْجمعِ فيهمَا والعورة كل مَا يستحيا مِنْهُ إِذا ظهر والروعة الْفَزع (قَوْله وَإِن أغتال من تحتي) قَالَ وَكِيع بن الْجراح يَعْنِي الْخَسْف",
    "sound": "11.mp3"
  },
  {
    "count": 3,
    "zekr": "بِسـمِ اللهِ الذي لا يَضُـرُّ مَعَ اسمِـهِ شَيءٌ في الأرْضِ وَلا في السّمـاءِ وَهـوَ السّمـيعُ العَلـيم.",
    "source": "الحَدِيث أخرجه أهل السّنَن الْأَرْبَع وَابْن حبَان كَمَا قَالَ المُصَنّف  وَهُوَ من حَدِيث عُثْمَان بن عَفَّان  قَالَ التِّرْمِذِيّ بعد إِخْرَاجه حسن غَرِيب صَحِيح وَصَححهُ أَيْضا ابْن حبَان وَأخرجه أَيْضا من حَدِيثه الْحَاكِم وَقَالَ صَحِيح الْإِسْنَاد وَتَمام الحَدِيث بعد قَوْله ثَلَاث مَرَّات فَلَا يضرّهُ شَيْء وَفِي وَلَفظ فيضره شَيْء وَأول الحَدِيث مَا من عبد يَقُول فِي صباح كل يَوْم وَمَسَاء كل لَيْلَة بِسم الله الخ وَفِي الحَدِيث دَلِيل على أَن هَذِه الْكَلِمَات تدفع عَن قَائِلهَا كل ضرّ كَائِنا مَا كَانَ وَأَنه لَا يصاب بِشَيْء فِي لَيْلَة وَلَا فِي نَهَاره إِذا قَالَهَا فِي اللَّيْل وَالنَّهَار وَكَانَ أبان بن عُثْمَان قد أَصَابَهُ طرف فالج فَجعل الرجل الَّذِي سمع مِنْهُ هَذَا الحَدِيث ينظر إِلَيْهِ فَقَالَ لَهُ أبان مَا تنظر أما أَن الحَدِيث كَمَا حدثتك وَلَكِنِّي لم أَقَله يَوْمئِذٍ ليمض الله عَليّ قدره (قَوْله فِي الصَّباح والمساء) قَالَ المُصَنّف فِي كِتَابه الَّذِي سَمَّاهُ مِفْتَاح الْحصن إِن الصَّباح من طُلُوع الْفجْر إِلَى غرُوب الشَّمْس وَالْمرَاد بالمساء من الْغُرُوب إِلَى الْفجْر وَقد أبعد من قَالَ أَن الْمسَاء يدْخل وقته بالزوال فَإِن أَرَادَ دُخُول العشى فقريب وَإِن أَرَادَ الْمسَاء فبعيد فَإِن الله  يَقُول ﴿حِين تمسون وَحين تُصبحُونَ﴾ فقابل الْمسَاء بالصباح",
    "sound": "12.mp3"
  },
  {
    "count": 3,
    "zekr": "سُبْحَانَ اللَّهِ وَبِحَمْدِهِ عَدَدَ خَلْقِهِ، وَرِضَا نَفْسِهِ، وَزِنَةَ عَرْشِهِ، وَمِدَادَ كَلِمَاتِهِ",
    "source": "أخرجه مسلم في \"صحيحه\"، كتاب : الذكر والدعاء والتوبة والاستغفار  باب  التسبيح أول النهار وعند النوم (8/ 83) رقم (2726).",
    "sound": "13.mp3"
  },
  {
    "count": 3,
    "zekr": "اللهم إني أعوذ بك أن أشرك بك وأنا أعلم، وأستغفرك لما لا أعلم",
    "source": "فهذا الدعاء يقال إذا خاف العبد على نفسه شيئا من الرياء، أو أراد أن يتقي أبواب الشرك كبيرها وصغيرها، فعن أبي موسى الأشعري قال: خطبنا رسول الله صلى الله عليه وسلم ذات يوم فقال: يا أيها الناس اتقوا هذا الشرك، فإنه أخفى من دبيب النمل. فقال له من شاء الله أن يقول: وكيف نتقيه وهو أخفى من دبيب النمل يا رسول الله ؟ قال: قولوا: اللهم إنا نعوذ بك من أن نشرك بك شيئا نعلمه، ونستغفرك لما لا نعلمه. رواه أحمد، وحسنه الألباني. \n وروى البخاري في الأدب المفرد عن معقل بن يسار قال: انطلقت مع أبي بكر الصديق رضي الله عنه إلى النبي صلى الله عليه وسلم فقال: يا أبا بكر ! للشرك فيكم أخفى من دبيب النمل. فقال أبو بكر: وهل الشرك إلا من جعل مع الله إلهاً آخر؟ فقال النبي صلى الله عليه وسلم: والذي نفسي بيده، للشرك أخفى من دبيب النمل، ألا أدلك على شيء إذا قلته ذهب عنك قليله وكثيره؟ قال: قل: اللهم إني أعوذ بك أن أشرك بك وأنا أعلم، وأستغفرك لما لا أعلم. وصححه الألباني.",
    "sound": "14.mp3"
  },
  {
    "count": 3,
    "zekr": "أعوذ بِكَلِمَات الله التامات من شَرّ مَا خلق",
    "source": "الحَدِيث أخرجه التِّرْمِذِيّ وَالطَّبَرَانِيّ فِي الْأَوْسَط كَمَا قَالَ المُصَنّف  وَهُوَ من حَدِيث أبي هُرَيْرَة  رَوَاهُ الطَّبَرَانِيّ من ثَلَاث طرق قَالَ الهيثمي رِوَايَتَانِ مِنْهَا رجالهما ثِقَات وَفِي بَعضهم خلاف وَلَفظ التِّرْمِذِيّ من قَالَ حِين يُمْسِي وَحين يصبح ثَلَاث مَرَّات أعوذ بِكَلِمَات الله التامات من شَرّ مَا خلق لم تضره حمة تِلْكَ اللَّيْلَة وَقَالَ هَذَا حَدِيث حسن وأصل الحَدِيث فِي صَحِيح مُسلم وَأهل السّنَن بِلَفْظ أَنه جَاءَ رجل إِلَى النَّبِي ﷺ قَالَ يَا رَسُول الله لقِيت عقربا لدغني البارحة فَقَالَ أما قلت حِين أمسيت أعوذ بِكَلِمَات الله التامات من شَرّ مَا خلق وَظَاهره انه يَقُولهَا مرّة وَاحِدَة (قَوْله أعوذ بِكَلِمَات الله التامات) قَالَ الْهَرَوِيّ وَغَيره الْكَلِمَات هِيَ الْقرَان والتامات قيل هِيَ الكاملات وَالْمعْنَى انه لَا يدخلهَا نقص وَلَا عيب كَمَا يدْخل فِي كَلَام النَّاس وَقيل هِيَ النافعات الكافيات الشافيات من كل مَا يتَعَوَّذ مِنْهُ",
    "sound": "15.mp3"
  },
  {
    "count": 1,
    "zekr": "اللّهُـمَّ فاطِـرَ السّماواتِ وَالأرْضِ عالِـمَ الغَـيْبِ وَالشّـهادَةِ، رَبَّ كـلِّ شَـيءٍ وَمَليـكَه، أَعـوذُ بِكَ مِن شَـرِّ نَفْسـي وَمِن شَـرِّ الشَّيْـطانِ وَشِرْكِهِ، وَأَنْ أَقْتَـرِفَ عَلـى نَفْسـي سوءاً أَوْ أَجُـرَّهُ إِلـى مُسْـلِم.",
    "source": "الحَدِيث أخرجه أَبُو دَاوُد وَالتِّرْمِذِيّ وَابْن حبَان كَمَا قَالَ المُصَنّف  وَهُوَ من حَدِيث أبي بكر الصّديق  وَقد أخرجه أَيْضا النَّسَائِيّ من حَدِيثه وَالْحَاكِم وَقَالَ صَحِيح الْإِسْنَاد وَصَححهُ ابْن حبَان وَأول الحَدِيث أَن أَبَا بكر  قَالَ يَا رَسُول الله مرني بِكَلِمَات أقولهن إِذا أَصبَحت وَإِذا أمسيت قَالَ قل اللَّهُمَّ فاطر السَّمَوَات الخ وَزَاد فِي أواخرهن قَالَ قلها إِذا أَصبَحت وَإِذا أمسيت وَإِذا أخذت مضجعك وَزَاد التِّرْمِذِيّ من طَرِيق أُخْرَى وَأَن نقترف على أَنْفُسنَا سوءا أَو نجره إِلَى مُسلم (قَوْله وشركه) قَالَ الْخطابِيّ روى على وَجْهَيْن أَحدهمَا بِكَسْر الشين وَسُكُون الرَّاء وَمَعْنَاهُ مَا يَدْعُو إِلَيْهِ الشَّيْطَان ويوسوس بِهِ من الْإِشْرَاك بِاللَّه  وَالثَّانِي بِفَتْح الشين وَالرَّاء يُرِيد حبائل الشَّيْطَان ومصائده (وَأَن أقترف على نَفسِي سوءا أَو أجره إِلَى مُسلم (طس) وَإِن نقترف على أَنْفُسنَا سوءا أَو نجره إِلَى مُسلم (ت» هَذَا طرف من الحَدِيث الأول كَمَا قدمنَا وَقد نسب المُصَنّف اللَّفْظ الأول إِلَى الطَّبَرَانِيّ فِي الْأَوْسَط وَاللَّفْظ الثَّانِي إِلَى التِّرْمِذِيّ وَقد قدمنَا أَنه لفظ التِّرْمِذِيّ",
    "sound": "16.mp3"
  },
  {
    "count": 4,
    "zekr": "اللّهُـمَّ إِنِّـي أَصْبَـحْتُ أُشْـهِدُك، وَأُشْـهِدُ حَمَلَـةَ عَـرْشِـك، وَمَلَائِكَتَكَ، وَجَمـيعَ خَلْـقِك، بأَنَّـكَ أَنْـتَ اللهُ لا إلهَ إلاّ أَنْـتَ وَحْـدَكَ لا شَريكَ لَـك، وَأَنَّ ُ مُحَمّـداً عَبْـدُكَ وَرَسـولُـك.",
    "source": "الحَدِيث أخرجه أَبُو دَاوُد وَالتِّرْمِذِيّ كَمَا قَالَ المُصَنّف  وَهُوَ من حَدِيث أنس بن مَالك  وَأخرجه أَيْضا من حَدِيثه النَّسَائِيّ وَلَفظ الحَدِيث عِنْد هَؤُلَاءِ من قَالَ حِين يصبح أَو حِين يُمْسِي اللَّهُمَّ إِنِّي أَصبَحت أشهدك وَأشْهد حَملَة عرشك وملائكتك وَجَمِيع خلقك أَنَّك أَنْت الله لَا إِلَه إِلَّا أَنْت وَحدك لَا شريك لَك وَأَن مُحَمَّدًا عَبدك وَرَسُولك أعتق الله ربعه من النَّار وَمن قَالَهَا مرَّتَيْنِ أعتق الله نصفه من النَّار وَمن قَالَهَا ثَلَاثًا أعتق الله ثَلَاثَة أَرْبَاعه فَإِن قَالَهَا أَرْبعا أعْتقهُ الله من النَّار وَقد جود النَّوَوِيّ إِسْنَاد هَذَا الحَدِيث وَالْمُصَنّف اقْتصر على بعضه كَمَا ترى",
    "sound": "17.mp3"
  },
  {
    "count": 7,
    "zekr": "حَسْبِـيَ اللّهُ لا إلهَ إلاّ هُوَ عَلَـيهِ تَوَكَّـلتُ وَهُوَ رَبُّ العَرْشِ العَظـيم.",
    "source": "الحَدِيث أخرجه ابْن السّني كَمَا قَالَ المُصَنّف  وَهُوَ من حَدِيث أبي الدَّرْدَاء  قَالَ ابْن السّني فِي عمل الْيَوْم وَاللَّيْلَة حَدثنِي مُحَمَّد بن سُلَيْمَان الْجرْمِي حَدثنَا أَحْمد بن عبد الرَّزَّاق الدِّمَشْقِي قَالَ حَدثنِي جدي عبد الرَّزَّاق بن مُسلم الدِّمَشْقِي حَدثنَا مدرك بن سعد قَالَ سَمِعت يُونُس بن ميسرَة بن حَلبس يَقُول سَمِعت أم الدَّرْدَاء عَن أبي الدَّرْدَاء  فَذكره ومدرك بن سعيد لَا بَأْس بِهِ وَأخرجه أَيْضا من حَدِيثه ابْن عَسَاكِر وَفِي الحَدِيث زِيَادَة فِي أَوله بِلَفْظ من قَالَ حِين يصبح وَحين يُمْسِي وَفِي آخِره زِيَادَة أَيْضا بعد قَوْله سبع مَرَّات وَهِي كَفاهُ الله مَا أهمه من أَمر الدُّنْيَا وَالْآخِرَة صَادِقا بهَا أم كَاذِبًا وَأخرجه أَيْضا أَبُو دَاوُد مَوْقُوفا على أبي الدَّرْدَاء وَله حكم الرّفْع",
    "sound": "18.mp3"
  },
  {
    "count": 3,
    "zekr": "ييَا حَيّ يَا قيوم بِرَحْمَتك أستغيث أصلح لي شأني كُله وَلَا تَكِلنِي إِلَى نَفسِي طرفَة عين",
    "source": "الحَدِيث أخرجه النَّسَائِيّ وَالْحَاكِم فِي الْمُسْتَدْرك كَمَا قَالَ المُصَنّف  وَهُوَ من حَدِيث أنس  قَالَ قَالَ رَسُول الله ﷺ لفاطمة مَا يمنعك أَن تسمعي مَا أوصيك بِهِ تَقُولِينَ إِذا أَصبَحت وَإِذا أمسيت يَا حَيّ يَا قيوم بِرَحْمَتك أستغيث أصلح لي شأني كُله وَلَا تَكِلنِي إِلَى نَفسِي طرفَة عين قَالَ الْحَاكِم صَحِيح على شَرط الشَّيْخَيْنِ وَأخرجه أَيْضا الْبَزَّار وَالطَّبَرَانِيّ قَالَ الْمُنْذِرِيّ بِإِسْنَاد صَحِيح وَقَالَ الهيثمي رِجَاله رِجَاله الصَّحِيح غير عُثْمَان بن موهب فَهُوَ ثِقَة والْحَدِيث من جَوَامِع الْكَلم لِأَن صَلَاح الشَّأْن كُله يتَنَاوَل جَمِيع أُمُور الدُّنْيَا والأخرة فَلَا يفز شَيْء مِنْهَا فيفوز قَائِل هَذَا إِذا تفضل الله عَلَيْهِ بالإجابة بخيري الدُّنْيَا وَالْآخِرَة مَعَ مَا فِي الحَدِيث من تَفْوِيض الْأُمُور إِلَى الرب  فَإِن ذَلِك من أعظم الْإِيمَان وَأجل خصاله وأشرف أَنْوَاعه",
    "sound": "19.mp3"
  },
  {
    "count": 3,
    "zekr": "اللَّهُمَّ إِنِّي أَعُوذُ بِكَ مِنْ الْهَمِّ وَالْحَزَنِ، وَأَعُوذُ بِكَ مِنْ الْعَجْزِ وَالْكَسَلِ، وَأَعُوذُ بِكَ مِنْ الْجُبْنِ وَالْبُخْلِ، وَأَعُوذُ بِكَ مِنْ غَلَبَةِ الدَّيْنِ، وَقَهْرِ الرِّجَالِ.",
    "source": "الحَدِيث أخرجه أَبُو دَاوُد كَمَا قَالَ المُصَنّف  وَهُوَ من حَدِيث أبي سعيد الْخُدْرِيّ  قَالَ دخل رَسُول الله ﷺ ذَات يَوْم الْمَسْجِد فَإِذا هُوَ بِرَجُل من الْأَنْصَار يُقَال لَهُ أَبُو أُمَامَة فَقَالَ يَا أَبَا أُمَامَة مَا لي أَرَاك جَالِسا فِي الْمَسْجِد فِي غير وَقت صَلَاة قَالَ هموم لزمتني وديون يَا رَسُول الله قَالَ أَفلا أعلمك كلَاما إِذا قلته أذهب الله همك وَقضى دينك قلت بلَى يَا رَسُول الله قَالَ قل إِذا أَصبَحت وَإِذا أمسيت اللَّهُمَّ إِنِّي أعوذ بك من الْهم والحزن وَأَعُوذ بك من الْعَجز والكسل وَأَعُوذ بك من الْجُبْن وَالْبخل وَأَعُوذ بك من غَلَبَة الدّين وقهر الرِّجَال قَالَ فَفعلت ذَلِك فَأذْهب الله همي وَقضى ديني وَلَا مطْعن فِي إِسْنَاد هَذَا الحَدِيث وَفِي الْبَاب مَا أخرجه أَحْمد وَالْبُخَارِيّ وَمُسلم وَغَيرهم من حَدِيث أنس وَلَفظ البُخَارِيّ اللَّهُمَّ إِنِّي أعوذ بك من الْهم والحزن وَالْعجز والكسل والجبن وَالْبخل وضلع الدّين وَغَلَبَة الرِّجَال (قَوْله أعوذ بك من الْهم والحزن) بِضَم الْحَاء الْمُهْملَة وَإِسْكَان الزَّاي وَهُوَ الْغم على الْفَائِت وبفتحهما ضد السرُور وَقيل وَالْفرق بَين الْهم والحزن أَن الْهم إِنَّمَا يكون لأمر متوقع وَأَن الْحزن يكون من أَمر قد وَقع وَقيل أَن الْفرق بَين الْهم والحزن أَن الْحزن على الْمَاضِي والهم للمستقبل وَقيل الْفرق بَينهمَا بالشدة والضعف فالهم أَشد فِي النَّفس من الْحزن لما يحصل فِيهَا من الْغم بِسَبَبِهِ (قَوْله من الْعَجز) الْعَجز ضد الْقُدْرَة وَأَصله التَّأَخُّر عَن الشَّيْء اسْتعْمل فِي مُقَابلَة الْقُدْرَة (قَوْله والكسل) هُوَ التثاقل عَن الْأُمُور (قَوْله والجبن) هُوَ بِضَم الْجِيم وَإِسْكَان الْمُوَحدَة وَبِضَمِّهَا صفة الجبان (قَوْله وَالْبخل) فِيهِ أَربع لُغَات قريء بهَا وَهِي ضم الْبَاء وَالْخَاء وفتحهما وَضم الْبَاء وَفتحهَا مَعَ إسكان الْخَاء (قَوْله وقهر الرِّجَال) هُوَ شدَّة تسلطهم بِغَيْر حق تغلبا وجدلا",
    "sound": "20.mp3"
  },
  {
    "count": 1,
    "zekr": "اللّهـمَّ أَنْتَ رَبِّـي لا إلهَ إلاّ أَنْتَ، خَلَقْتَنـي وَأَنا عَبْـدُك، وَأَنا عَلـى عَهْـدِكَ وَوَعْـدِكَ ما اسْتَـطَعْـت، أَعـوذُ بِكَ مِنْ شَـرِّ ما صَنَـعْت، أَبـوءُ لَـكَ بِنِعْـمَتِـكَ عَلَـيَّ وَأَبـوءُ بِذَنْـبي فَاغْفـِرْ لي فَإِنَّـهُ لا يَغْـفِرُ الذُّنـوبَ إِلاّ أَنْتَ.",
    "source": "لحَدِيث الأول أخرجه البُخَارِيّ كَمَا قَالَ المُصَنّف  وَهُوَ من حَدِيث شَدَّاد بن أَوْس  مَا عَن النَّبِي ﷺ قَالَ سيد الاسْتِغْفَار اللَّهُمَّ أَنْت رَبِّي الخ وَآخره إِذا قَالَه حِين يُمْسِي فَمَاتَ دخل الْجنَّة أَو كَانَ من أهل الْجنَّة وَإِذا قَالَه حِين يصبح فَمَاتَ من يَوْمه مثله وَأخرجه أَيْضا التِّرْمِذِيّ وَالنَّسَائِيّ وَاللَّفْظ الآخر أخرجه أَبُو دَاوُد وَابْن السّني كَمَا قَالَ المُصَنّف  وَهُوَ من حَدِيث أَوْس بن أَوْس وَأخرجه أَيْضا احْمَد فِي مُسْنده وَالْبُخَارِيّ وأوله سيد الاسْتِغْفَار أَن تَقول اللَّهُمَّ أَنْت رَبِّي الخ وَآخره من قَالَهَا من النَّهَار موقنا بهَا فَمَاتَ من يَوْمه قبل أَن يُمْسِي فَهُوَ من أهل الْجنَّة وَمن قَالَهَا من اللَّيْل وَهُوَ موقن بهَا فَمَاتَ قبل أَن يصبح فَهُوَ من أهل الْجنَّة قَالَ الطَّيِّبِيّ لما كَانَ هَذَا الدُّعَاء جَامعا لمعاني التَّوْبَة كلهَا استعير لَهُ اسْم السَّيِّد وَهُوَ فِي الأَصْل الرئيس الَّذِي يقْصد فِي الْحَوَائِج وَيرجع إِلَيْهِ فِي الْمُهِمَّات قَالَ ابْن أبي حَمْزَة جمع الحَدِيث من بديع الْمعَانِي وَحسن الْأَلْفَاظ مَا يحِق لَهُ أَن يُسمى بِسَيِّد الاسْتِغْفَار فَفِيهِ الْإِقْرَار لله وَحده بالألوهية ولنفسه بالعبودية وَالِاعْتِرَاف بِأَنَّهُ الْخَالِق وَالْإِقْرَار بالعهد الَّذِي أَخذ عَلَيْهِ والرجاء بِمَا وعد بِهِ والاستعاذة مِمَّا جنى بِهِ على نَفسه وَإِضَافَة النعم إِلَى موجدها وَإِضَافَة الذَّنب إِلَى نَفسه ورغبته فِي الْمَغْفِرَة واعترافه بِأَنَّهُ لَا يقدر على ذَلِك إِلَّا هُوَ (قَوْله وَأَنا على عَهْدك وَوَعدك) أَي مَا عاهدتك عَلَيْهِ وواعدتك من الْإِيمَان وإخلاص الطَّاعَة لَك وَقيل الْعَهْد مَا أَخذ فِي عَالم الذَّر والوعد مَا جَاءَ على لِسَان النَّبِي ﷺ أَن من مَاتَ لَا يُشْرك بِاللَّه دخل الْجنَّة وَمعنى مَا اسْتَطَعْت مُدَّة دوَام استطاعتي وَفِيه الِاعْتِرَاف بِالْعَجزِ والقصور وَمعنى أَبُوء لَك أعترف وألتزم قَالَ الطَّيِّبِيّ اعْترف أَولا بِأَنَّهُ أنعم عَلَيْهِ وَلم يُقَيِّدهُ ليشْمل كل إنعام ثمَّ اعْترف بالتقصير وَأَنه لم يقم بأَدَاء شكرها وعده ذَنبا مُبَالغَة فِي التَّقْصِير وهضم النَّفس ",
    "sound": "21.mp3"
  },
  {
    "count": 100,
    "zekr": "لَا إلَه إلّا اللهُ وَحْدَهُ لَا شَرِيكَ لَهُ، لَهُ الْمُلْكُ وَلَهُ الْحَمْدُ وَهُوَ عَلَى كُلِّ شَيْءِ قَدِيرِ.",
    "source": "الحَدِيث أخرجه أَبُو دَاوُد وَالنَّسَائِيّ كَمَا قَالَ المُصَنّف  وَهُوَ من حَدِيث أبي عَيَّاش الزرقي وَأخرجه أَيْضا أَحْمد وَابْن مَاجَه وَلَفظ الحَدِيث عَن أبي عَيَّاش أَن رَسُول الله ﷺ قَالَ من قَالَ إِذا أصبح لَا إِلَه إِلَّا الله وَحده لَا شريك لَهُ لَهُ الْملك وَله الْحَمد وَهُوَ على كل شَيْء قدير كَانَ لَهُ عدل رَقَبَة من ولد إِسْمَاعِيل وَكتب لَهُ عشر حَسَنَات وَحط عَنهُ عشر سيئات وَرفع لَهُ عشر دَرَجَات وَكَانَ فِي حرز من الشَّيْطَان حَتَّى يُمْسِي وان قَالَهَا إِذا أَمْسَى كَانَ لَهُ مثل ذَلِك حَتَّى يصبح قَالَ فِي حَدِيث حَمَّاد بن سَلمَة فَرَأى رجل رَسُول الله ﷺ فِيمَا يرى النَّائِم فَقَالَ يَا رَسُول الله إِن أَبَا عَيَّاش يحدث عَنْك بِكَذَا وَكَذَا فَقَالَ صدق أَبُو عَيَّاش هَذَا لفظ أبي دَاوُد وَقد ورد فِي التَّرْغِيب فِي هَذَا الذّكر غير مُقَيّد بِلَفْظ الصَّباح أَحَادِيث فَمِنْهَا مَا فِي الصَّحِيحَيْنِ وَغَيرهمَا من حَدِيث أبي أَيُّوب الْأنْصَارِيّ ﵁ أَن رَسُول الله ﷺ قَالَ من قَالَ لَا إِلَه إِلَّا الله وَحده لَا شريك لَهُ لَهُ الْملك وَله الْحَمد وَهُوَ على كل شَيْء قدير عشر مَرَّات كَانَ كمن أعتق أَرْبَعَة أنفس من ولد إِسْمَاعِيل وَفِي رِوَايَة لِأَحْمَد وَالطَّبَرَانِيّ من هَذَا الحَدِيث كن كَعدْل عشر رِقَاب من ولد إِسْمَاعِيل وَمِنْهَا مَا أخرجه أَحْمد من حَدِيث الْبَراء بِإِسْنَاد رِجَاله رجال الصَّحِيح بِلَفْظ من قَالَ لَا إِلَه إِلَّا الله وَحده لَا شريك لَهُ لَهُ الْملك وَله الْحَمد وَهُوَ على لَك شَيْء قدير فَهُوَ كعتق نسمَة وَأخرجه أَيْضا التِّرْمِذِيّ وَقَالَ حَدِيث حسن صَحِيح وَصَححهُ ابْن حبَان وَمِنْهَا مَا أخرجه الطَّبَرَانِيّ من حَدِيث أبي أُمَامَة  بِإِسْنَاد رِجَاله رجال الصَّحِيح أَن رَسُول الله ﷺ قَالَ من قَالَ لَا إِلَه إِلَّا الله وَحده لَا شريك لَهُ لَهُ الْملك وَله الْحَمد وَهُوَ على كل شَيْء قدير لم يسبقها عمل وَلم تبْق مَعهَا سَيِّئَة وَفِي الْبَاب أَحَادِيث",
    "sound": "22.mp3"
  },
  {
    "count": 100,
    "zekr": "سُبْحـانَ اللهِ وَبِحَمْـدِهِ.",
    "source": "الحَدِيث أخرجه مُسلم وَأَبُو دَاوُد كَمَا قَالَ المُصَنّف  وَهُوَ من حَدِيث أبي هُرَيْرَة قَالَ قَالَ رَسُول الله ﷺ من قَالَ حِين يصبح وَحين يُمْسِي سُبْحَانَ الله وَبِحَمْدِهِ مائَة مرّة لم يَأْتِ أحد بِأَفْضَل مِمَّا جَاءَ بِهِ إِلَّا أحد قَالَ مثل مَا قَالَ أَو زَاد عَلَيْهِ وَأخرجه أَيْضا التِّرْمِذِيّ وَالنَّسَائِيّ وَاللَّفْظ الأول الَّذِي ذكره المُصَنّف هُوَ لفظ مُسلم وَالتِّرْمِذِيّ وَالنَّسَائِيّ وَاللَّفْظ الآخر هُوَ لفظ أبي دَاوُد وَرَوَاهُ الْحَاكِم من حَدِيثه فِي الْمُسْتَدْرك وَقَالَ صَحِيح على شَرط مُسلم وَلَفظه من قَالَ إِذا أصبح مائَة مرّة وَإِذا أَمْسَى مائَة مرّة سُبْحَانَ الله الْعَظِيم وَبِحَمْدِهِ غفرت ذنُوبه وَإِن كَانَت مثل زبد الْبَحْر وَرَوَاهُ أَيْضا من حَدِيثه ابْن حبَان فِي صَحِيحه مثل لفظ الْحَاكِم",
    "sound": "23.mp3"
  },
  {
    "count": 10,
    "zekr": "اللَّهُمَّ صَلِّ وَسَلِّمْ وَبَارِكْ على نَبِيِّنَا مُحمَّد.",
    "source": "الحَدِيث أخرجه الطَّبَرَانِيّ فِي الْكَبِير كَمَا قَالَ المُصَنّف  وَهُوَ من حَدِيث أبي الدَّرْدَاء قَالَ قَالَ رَسُول الله ﷺ من صلى عَليّ حِين يصبح عشرا وَحين يُمْسِي عشرا أَدْرَكته شَفَاعَتِي يَوْم الْقِيَامَة وَقد حسنه السُّيُوطِيّ وَقَالَ الْحَافِظ الْعِرَاقِيّ فِيهِ انْقِطَاع قَالَ الهيثمي رَوَاهُ الطَّبَرَانِيّ بِإِسْنَادَيْنِ أَحدهمَا جيد إِلَّا إِن فِيهِ انْقِطَاعًا لِأَن خَالِدا لم يسمع من أبي الدَّرْدَاء وَقد تقدّمت الْأَحَادِيث الْوَارِدَة فِي فضل الصَّلَاة عَلَيْهِ ﷺ وَاعْلَم أَن هَذِه الْأَعْدَاد الْوَارِدَة فِي هَذِه الْأَحَادِيث وَفِي جَمِيع هَذَا الْكتاب وَفِي سَائِر كتب الحَدِيث تَقْتَضِي أَن الْأجر الْمَذْكُور لفاعلها يحصل بِفِعْلِهَا فَإِن نقص من ذَلِك من أجره بِقَدرِهِ لِأَن الله سُبْحَانَهُ لَا يضيع عمل عَامل وَإِن زَاد على الْعدَد الْمَذْكُور حصل لَهُ الْأجر بِالْعدَدِ الْمُقدر وَاسْتحق ثَوَاب مَا زَاد وَقد قيل أَنه لَا يسْتَحق الْأجر الْمُرَتّب على الْعدَد إِلَّا إِذا اقْتصر عَلَيْهِ من غير زِيَادَة وَلَا نُقْصَان وَلَيْسَ ذَلِك بصواب إِلَّا مَا ورد النَّهْي عَن الزِّيَادَة فِيهِ كزيادة الرَّكْعَات وَزِيَادَة غسلات الْوضُوء وَنَحْو ذَلِك",
    "sound": "24.mp3"
  },
  {
    "count": 1,
    "zekr": "أَصْبَحْنَا وَأصْبح الْملك لله رب الْعَالمين اللَّهُمَّ إِنِّي أَسأَلك خير هَذَا الْيَوْم فَتحه وَنَصره ونوره وبركته وهداه وَأَعُوذ بك من شَرّ مَا فِيهِ وَشر مَا بعده",
    "source": "الحَدِيث أخرجه أَبُو دَاوُد كَمَا قَالَ المُصَنّف رَحمَه الله وَهُوَ من حَدِيث أبي مَالك الْأَشْعَرِيّ رَضِي الله عَنهُ وَفِي إِسْنَاده إِسْمَاعِيل بن عَيَّاش وَفِيه مقَال مَعْرُوف وَفِي إِسْنَاده أَيْضا ضَمْضَم بن زرْعَة الْحَضْرَمِيّ ضعفه أَبُو حَاتِم وَلَكِن قد وَثَّقَهُ ابْن معِين وَابْن حبَان وَفِي آخِره زِيَادَة عِنْد أبي دَاوُد وَهِي ثمَّ إِذا امسى فَلْيقل مثل ذَلِك وَقد وَقع الاختباط فِي نسخ هَذَا الْكتاب فَفِي بَعْضهَا أَصْبَحْنَا كَمَا هُوَ هُنَا وَفِي بَعْضهَا أمسينا وَوَقع تَغْيِير للضمائر بالتذكير والتأنيث مُرَاعَاة للفظ الصَّباح وَلَفظ الْمسَاء وَاللَّيْلَة وَالْيَوْم وَأول هَذَا الحَدِيث بِلَفْظ إِذا أصبح أحدكُم فَلْيقل أَصْبَحْنَا وَقد أخرجه الطَّبَرَانِيّ فِي الْكَبِير",
    "sound": "25.mp3"
  },
  {
    "count": 1,
    "zekr": "للَّهُمَّ إِنِّي أَسْأَلُكَ عِلْمًا نَافِعًا، وَرِزْقًا طَيِّبًا، وَعَمَلًا مُتَقَبَّلًا ",
    "source": "حَدَّثَنَا أَبُو بَكْرِ بْنُ أَبِي شَيْبَةَ ، قَالَ : حَدَّثَنَا شَبَابَةُ ، قَالَ : حَدَّثَنَا شُعْبَةُ ، عَنْ مُوسَى بْنِ أَبِي عَائِشَةَ ، عَنْ مَوْلًى لِأُمِّ سَلَمَةَ   ، عَنْ أُمِّ سَلَمَةَ ، أَنَّ النَّبِيَّ صَلَّى اللَّهُ عَلَيْهِ وَسَلَّمَ كَانَ يَقُولُ إِذَا صَلَّى الصُّبْحَ حِينَ يُسَلِّمُ : \" اللَّهُمَّ إِنِّي أَسْأَلُكَ عِلْمًا نَافِعًا، وَرِزْقًا طَيِّبًا، وَعَمَلًا مُتَقَبَّلًا \". \n أخرجه ابن ماجه في \"السنن\"، كتاب : إقامة الصلاة والسنة فيها  باب  ما يقال بعد التسليم (2/ 183) رقم (925).",
    "sound": "26.mp3"
  },
  {
    "count": 100,
    "zekr": "أسْتَغْفِرُ اللهَ وَأتُوبُ إلَيْه.",
    "source": "كتب له مائة حسنة ومحيت عنه مائة سيئة وكانت له حرزا من الشيطان يومه ذلك حتى يمسي",
    "sound": "27.mp3"
  },
  {
    "count": 1,
    "zekr": "تم الانتهاء من أذكار الصباح ^_^\nاتمنى لك يوم جميل .. مثل قلبك ❤",
    "source": ""
  }
]